ubuntu_namer/__init__.py
ubuntu_namer/__main__.py
ubuntu_namer/lambda_function.py
ubuntu_namer/names.py
ubuntu_namer-0.3.1.dist-info/LICENSE
ubuntu_namer-0.3.1.dist-info/METADATA
ubuntu_namer-0.3.1.dist-info/WHEEL
ubuntu_namer-0.3.1.dist-info/entry_points.txt
ubuntu_namer-0.3.1.dist-info/RECORD
