Metadata-Version: 2.1
Name: ubuntu-namer
Version: 0.3.1
Summary: Python port of ubuntu-name-generator
Home-page: https://github.com/crypdick/ubuntu-namer
License: MIT
Author: Richard Decal
Requires-Python: >=3.7,<4.0
Classifier: Development Status :: 3 - Alpha
Classifier: Intended Audience :: Developers
Classifier: License :: OSI Approved :: MIT License
Classifier: Operating System :: OS Independent
Classifier: Programming Language :: Python :: 3
Classifier: Programming Language :: Python :: 3.7
Classifier: Programming Language :: Python :: 3.8
Classifier: Programming Language :: Python :: 3.9
Classifier: Programming Language :: Python :: 3.10
Classifier: Programming Language :: Python :: 3.11
Classifier: Programming Language :: Python :: 3
Classifier: Programming Language :: Python :: 3.7
Classifier: Programming Language :: Python :: 3.8
Classifier: Programming Language :: Python :: 3.9
Classifier: Topic :: Software Development :: Libraries :: Python Modules
Requires-Dist: importlib_metadata (>=4.5,<7.0) ; python_version < "3.8"
Requires-Dist: rich (>=12.5.1,<13.0.0)
Requires-Dist: typer[all] (>=0.6.1,<0.8.0)
Project-URL: Repository, https://github.com/crypdick/ubuntu-namer
